birdlib/adblock.py
birdlib/bookmarks.py
birdlib/crypt.py
birdlib-0.5.2.dist-info/METADATA
birdlib-0.5.2.dist-info/WHEEL
birdlib-0.5.2.dist-info/top_level.txt
birdlib-0.5.2.dist-info/RECORD
